{
    "count": 1,
    "total": 1,
    "orders": [
        {
            "number": 124,
            "vendorNumber": "124",
            "externalTransactionId": "6154582149",
            "created": "2014-05-06 16:28:06",
            "paymentStatus": "ACCEPTED",
            "fulfillmentStatus": "NEW",
            "paymentMethod": "Credit card",
            "billingPerson": {
                "name": "John Doe",
                "companyName": "",
                "street": "123 Ladida Ln",
                "city": "Salinas",
                "countryCode": "US",
                "postalCode": "93907",
                "stateOrProvinceCode": "CA",
                "stateName": "California",
                "countryName": "United States",
                "phone": "555 555 5555"
            },
            "paymentParameters": {},
            "avsMessage": "Five digit ZIP matches, Address (Street) does not",
            "customerId": 3449981,
            "customerName": "John Doe",
            "customerEmail": "John@doe.com",
            "customerIP": "72.14.86.186",
            "customerCountryCodeByIP": "US",
            "subtotalCost": 29.95,
            "couponDiscountCost": 0,
            "volumeDiscountCost": 0,
            "discountCost": 0,
            "shippingCost": 0,
            "taxCost": 0,
            "totalCost": 29.95,
            "items": [
                {
                    "sku": "00046",
                    "name": "Widget",
                    "quantity": 1,
                    "price": 29.95,
                    "weight": 0,
                    "productId": 14232061,
                    "options": [
                        {
                            "name": "Multiple year discount",
                            "type": "SELECT",
                            "value": "1-year renewal"
                        }
                    ],
                    "categoryId": 2830026,
                    "taxes": []
                }
            ],
            "lastChangeDate": "2014-05-06 20:28:51"
        }
    ]
}